jiyan_wugan/__init__.py
jiyan_wugan/core.py
jiyan_wugan/sp.py
jiyan_wugan/util.py
jiyan_wugan/js/__init__.py
jiyan_wugan/js/evn.js
jiyan_wugan/js/jy.js
jiyan_wugan/js/sdk.js
jiyan_wugan-0.1.8.dist-info/METADATA
jiyan_wugan-0.1.8.dist-info/WHEEL
jiyan_wugan-0.1.8.dist-info/top_level.txt
jiyan_wugan-0.1.8.dist-info/RECORD
