Metadata-Version: 2.4
Name: jiyan_wugan
Version: 0.1.8
Summary: 过无感验证
Home-page: 
Author: yeeye
Author-email: d258036653@gmail.com
Classifier: Programming Language :: Python :: 3
Classifier: License :: OSI Approved :: MIT License
Classifier: Operating System :: OS Independent
Requires-Python: >=3.6
Requires-Dist: PyExecJS
Requires-Dist: requests
Dynamic: author
Dynamic: author-email
Dynamic: classifier
Dynamic: requires-dist
Dynamic: requires-python
Dynamic: summary
